{
  "459826": {
    "type": "PM2",
    "value": 66,
    "timestamp": {
      "year": 2022,
      "month": 4,
      "day": 7
    }
  },
  "111475": {
    "type": "CARBON",
    "value": 1362,
    "timestamp": {
      "year": 2022,
      "month": 4,
      "day": 7
    }
  },
  "189700": {
    "type": "PM2",
    "value": 83,
    "timestamp": {
      "year": 2022,
      "month": 4,
      "day": 7
    }
  },
  "71075": {
    "type": "PM10",
    "value": 110,
    "timestamp": {
      "year": 2022,
      "month": 4,
      "day": 7
    }
  },
  "188503": {
    "type": "PM10",
    "value": 93,
    "timestamp": {
      "year": 2022,
      "month": 4,
      "day": 7
    }
  },
  "189101": {
    "type": "PM2",
    "value": 83,
    "timestamp": {
      "year": 2022,
      "month": 4,
      "day": 7
    }
  },
  "222878": {
    "type": "HUMIDITY",
    "value": 68,
    "timestamp": {
      "year": 2022,
      "month": 4,
      "day": 7
    }
  },
  "58205": {
    "type": "PM10",
    "value": 47,
    "timestamp": {
      "year": 2022,
      "month": 4,
      "day": 7
    }
  },
  "30301": {
    "type": "PM2",
    "value": 27,
    "timestamp": {
      "year": 2022,
      "month": 4,
      "day": 7
    }
  },
  "125921": {
    "type": "TEMPERATURE",
    "value": 29,
    "timestamp": {
      "year": 2022,
      "month": 4,
      "day": 7
    }
  },
  "389756": {
    "type": "PM2",
    "value": 53,
    "timestamp": {
      "year": 2022,
      "month": 4,
      "day": 7
    }
  },
  "13741": {
    "type": "HUMIDITY",
    "value": 78,
    "timestamp": {
      "year": 2022,
      "month": 4,
      "day": 7
    }
  },
  "85466": {
    "type": "CARBON",
    "value": 468,
    "timestamp": {
      "year": 2022,
      "month": 4,
      "day": 7
    }
  },
  "413651": {
    "type": "TEMPERATURE",
    "value": 31,
    "timestamp": {
      "year": 2022,
      "month": 4,
      "day": 7
    }
  },
  "498566": {
    "type": "CARBON",
    "value": 370,
    "timestamp": {
      "year": 2022,
      "month": 4,
      "day": 7
    }
  },
  "11653": {
    "type": "WIND",
    "value": 17,
    "timestamp": {
      "year": 2022,
      "month": 4,
      "day": 7
    }
  },
  "13655": {
    "type": "HUMIDITY",
    "value": 76,
    "timestamp": {
      "year": 2022,
      "month": 4,
      "day": 7
    }
  }
}